{"cameraMode":{"drawMode":0,"name":"Shaded","section":"Shading Mode"},"sceneLighting":true,"audioPlay":false,"sceneViewState":{"m_AlwaysRefresh":false,"showFog":true,"showSkybox":true,"showFlares":true,"showImageEffects":true,"showParticleSystems":true,"showVisualEffectGraphs":true,"m_FxEnabled":true},"in2DMode":false,"pivot":{"x":-12.463053703308106,"y":5.430561065673828,"z":-19.147506713867189},"rotation":{"x":-0.1068255677819252,"y":0.5574211478233337,"z":0.07274113595485687,"w":0.8201411962509155},"size":4.274346351623535,"orthographic":false}